Workbook

Sheet Dashboard
A1: ULTIMATE FINANCE OS
A2: Personal Finance Dashboard — Digital Product Studio
A3: Change the Report Month (H3) to view any period. | G3: Report Month: | H3: =DATE(YEAR(TODAY()),MONTH(TODAY()),1) -> 46235 | J3: Chart Data (auto-calculated — do not edit)
J4: Month | K4: Income | L4: Expenses | M4: Savings
A5: MONTHLY INCOME | C5: MONTHLY EXPENSES | E5: NET SAVINGS | G5: SAVINGS RATE % | J5: =EDATE(DATE(YEAR($H$3),MONTH($H$3),1),-11) -> 45901 | K5: =SUMIFS(Income!$D$4:$D$51,Income!$A$4:$A$51,">="&EDATE(DATE(YEAR($H$3),MONTH($H$3),1),-11),Income!$A$4:$A$51,"<"&EDATE(DATE(YEAR($H$3),MONTH($H$3),1),-10)) -> 0 | L5: =SUMIFS(Expenses!$E$4:$E$153,Expenses!$A$4:$A$153,">="&EDATE(DATE(YEAR($H$3),MONTH($H$3),1),-11),Expenses!$A$4:$A$153,"<"&EDATE(DATE(YEAR($H$3),MONTH($H$3),1),-10)) -> 0 | M5: =K5-L5 -> 0
A6: =SUMIFS(Income!$D$4:$D$51,Income!$A$4:$A$51,">="&DATE(YEAR($H$3),MONTH($H$3),1),Income!$A$4:$A$51,"<"&EDATE(DATE(YEAR($H$3),MONTH($H$3),1),1)) -> 10850 | C6: =SUMIFS(Expenses!$E$4:$E$153,Expenses!$A$4:$A$153,">="&DATE(YEAR($H$3),MONTH($H$3),1),Expenses!$A$4:$A$153,"<"&EDATE(DATE(YEAR($H$3),MONTH($H$3),1),1)) -> 2227.9 | E6: =A6-C6 -> 8622.1 | G6: =IFERROR(E6/A6,0) -> 0.79466359 | J6: =EDATE(DATE(YEAR($H$3),MONTH($H$3),1),-10) -> 45931 | K6: =SUMIFS(Income!$D$4:$D$51,Income!$A$4:$A$51,">="&EDATE(DATE(YEAR($H$3),MONTH($H$3),1),-10),Income!$A$4:$A$51,"<"&EDATE(DATE(YEAR($H$3),MONTH($H$3),1),-9)) -> 0 | L6: =SUMIFS(Expenses!$E$4:$E$153,Expenses!$A$4:$A$153,">="&EDATE(DATE(YEAR($H$3),MONTH($H$3),1),-10),Expenses!$A$4:$A$153,"<"&EDATE(DATE(YEAR($H$3),MONTH($H$3),1),-9)) -> 0 | M6: =K6-L6 -> 0
J7: =EDATE(DATE(YEAR($H$3),MONTH($H$3),1),-9) -> 45962 | K7: =SUMIFS(Income!$D$4:$D$51,Income!$A$4:$A$51,">="&EDATE(DATE(YEAR($H$3),MONTH($H$3),1),-9),Income!$A$4:$A$51,"<"&EDATE(DATE(YEAR($H$3),MONTH($H$3),1),-8)) -> 0 | L7: =SUMIFS(Expenses!$E$4:$E$153,Expenses!$A$4:$A$153,">="&EDATE(DATE(YEAR($H$3),MONTH($H$3),1),-9),Expenses!$A$4:$A$153,"<"&EDATE(DATE(YEAR($H$3),MONTH($H$3),1),-8)) -> 0 | M7: =K7-L7 -> 0
J8: =EDATE(DATE(YEAR($H$3),MONTH($H$3),1),-8) -> 45992 | K8: =SUMIFS(Income!$D$4:$D$51,Income!$A$4:$A$51,">="&EDATE(DATE(YEAR($H$3),MONTH($H$3),1),-8),Income!$A$4:$A$51,"<"&EDATE(DATE(YEAR($H$3),MONTH($H$3),1),-7)) -> 0 | L8: =SUMIFS(Expenses!$E$4:$E$153,Expenses!$A$4:$A$153,">="&EDATE(DATE(YEAR($H$3),MONTH($H$3),1),-8),Expenses!$A$4:$A$153,"<"&EDATE(DATE(YEAR($H$3),MONTH($H$3),1),-7)) -> 0 | M8: =K8-L8 -> 0
J9: =EDATE(DATE(YEAR($H$3),MONTH($H$3),1),-7) -> 46023 | K9: =SUMIFS(Income!$D$4:$D$51,Income!$A$4:$A$51,">="&EDATE(DATE(YEAR($H$3),MONTH($H$3),1),-7),Income!$A$4:$A$51,"<"&EDATE(DATE(YEAR($H$3),MONTH($H$3),1),-6)) -> 0 | L9: =SUMIFS(Expenses!$E$4:$E$153,Expenses!$A$4:$A$153,">="&EDATE(DATE(YEAR($H$3),MONTH($H$3),1),-7),Expenses!$A$4:$A$153,"<"&EDATE(DATE(YEAR($H$3),MONTH($H$3),1),-6)) -> 0 | M9: =K9-L9 -> 0
A10: BILLS DUE | C10: CURRENT NET WORTH | E10: AVG DAILY SPEND | G10: TOP EXPENSE CATEGORY | J10: =EDATE(DATE(YEAR($H$3),MONTH($H$3),1),-6) -> 46054 | K10: =SUMIFS(Income!$D$4:$D$51,Income!$A$4:$A$51,">="&EDATE(DATE(YEAR($H$3),MONTH($H$3),1),-6),Income!$A$4:$A$51,"<"&EDATE(DATE(YEAR($H$3),MONTH($H$3),1),-5)) -> 0 | L10: =SUMIFS(Expenses!$E$4:$E$153,Expenses!$A$4:$A$153,">="&EDATE(DATE(YEAR($H$3),MONTH($H$3),1),-6),Expenses!$A$4:$A$153,"<"&EDATE(DATE(YEAR($H$3),MONTH($H$3),1),-5)) -> 0 | M10: =K10-L10 -> 0
A11: =COUNTIFS(Bills!$D$4:$D$33,"Pending",Bills!$B$4:$B$33,"<="&EDATE(DATE(YEAR($H$3),MONTH($H$3),1),1)) -> 3 | C11: ='Net Worth'!E21 -> 45700 | E11: =IFERROR(C6/DAY((EDATE(DATE(YEAR($H$3),MONTH($H$3),1),1))-1),0) -> 71.867742 | G11: =INDEX(J20:J27,MATCH(MAX(K20:K27),K20:K27,0)) -> Housing | J11: =EDATE(DATE(YEAR($H$3),MONTH($H$3),1),-5) -> 46082 | K11: =SUMIFS(Income!$D$4:$D$51,Income!$A$4:$A$51,">="&EDATE(DATE(YEAR($H$3),MONTH($H$3),1),-5),Income!$A$4:$A$51,"<"&EDATE(DATE(YEAR($H$3),MONTH($H$3),1),-4)) -> 0 | L11: =SUMIFS(Expenses!$E$4:$E$153,Expenses!$A$4:$A$153,">="&EDATE(DATE(YEAR($H$3),MONTH($H$3),1),-5),Expenses!$A$4:$A$153,"<"&EDATE(DATE(YEAR($H$3),MONTH($H$3),1),-4)) -> 0 | M11: =K11-L11 -> 0
J12: =EDATE(DATE(YEAR($H$3),MONTH($H$3),1),-4) -> 46113 | K12: =SUMIFS(Income!$D$4:$D$51,Income!$A$4:$A$51,">="&EDATE(DATE(YEAR($H$3),MONTH($H$3),1),-4),Income!$A$4:$A$51,"<"&EDATE(DATE(YEAR($H$3),MONTH($H$3),1),-3)) -> 0 | L12: =SUMIFS(Expenses!$E$4:$E$153,Expenses!$A$4:$A$153,">="&EDATE(DATE(YEAR($H$3),MONTH($H$3),1),-4),Expenses!$A$4:$A$153,"<"&EDATE(DATE(YEAR($H$3),MONTH($H$3),1),-3)) -> 0 | M12: =K12-L12 -> 0
A13: ="$"&TEXT(SUMIFS(Bills!$C$4:$C$33,Bills!$D$4:$D$33,"Pending",Bills!$B$4:$B$33,"<="&EDATE(DATE(YEAR($H$3),MONTH($H$3),1),1)),"#,##0.00")&" pending" -> $485.00 pending | J13: =EDATE(DATE(YEAR($H$3),MONTH($H$3),1),-3) -> 46143 | K13: =SUMIFS(Income!$D$4:$D$51,Income!$A$4:$A$51,">="&EDATE(DATE(YEAR($H$3),MONTH($H$3),1),-3),Income!$A$4:$A$51,"<"&EDATE(DATE(YEAR($H$3),MONTH($H$3),1),-2)) -> 0 | L13: =SUMIFS(Expenses!$E$4:$E$153,Expenses!$A$4:$A$153,">="&EDATE(DATE(YEAR($H$3),MONTH($H$3),1),-3),Expenses!$A$4:$A$153,"<"&EDATE(DATE(YEAR($H$3),MONTH($H$3),1),-2)) -> 0 | M13: =K13-L13 -> 0
J14: =EDATE(DATE(YEAR($H$3),MONTH($H$3),1),-2) -> 46174 | K14: =SUMIFS(Income!$D$4:$D$51,Income!$A$4:$A$51,">="&EDATE(DATE(YEAR($H$3),MONTH($H$3),1),-2),Income!$A$4:$A$51,"<"&EDATE(DATE(YEAR($H$3),MONTH($H$3),1),-1)) -> 0 | L14: =SUMIFS(Expenses!$E$4:$E$153,Expenses!$A$4:$A$153,">="&EDATE(DATE(YEAR($H$3),MONTH($H$3),1),-2),Expenses!$A$4:$A$153,"<"&EDATE(DATE(YEAR($H$3),MONTH($H$3),1),-1)) -> 0 | M14: =K14-L14 -> 0
J15: =EDATE(DATE(YEAR($H$3),MONTH($H$3),1),-1) -> 46204 | K15: =SUMIFS(Income!$D$4:$D$51,Income!$A$4:$A$51,">="&EDATE(DATE(YEAR($H$3),MONTH($H$3),1),-1),Income!$A$4:$A$51,"<"&EDATE(DATE(YEAR($H$3),MONTH($H$3),1),0)) -> 0 | L15: =SUMIFS(Expenses!$E$4:$E$153,Expenses!$A$4:$A$153,">="&EDATE(DATE(YEAR($H$3),MONTH($H$3),1),-1),Expenses!$A$4:$A$153,"<"&EDATE(DATE(YEAR($H$3),MONTH($H$3),1),0)) -> 0 | M15: =K15-L15 -> 0
A16: CHARTS | J16: =EDATE(DATE(YEAR($H$3),MONTH($H$3),1),0) -> 46235 | K16: =SUMIFS(Income!$D$4:$D$51,Income!$A$4:$A$51,">="&EDATE(DATE(YEAR($H$3),MONTH($H$3),1),0),Income!$A$4:$A$51,"<"&EDATE(DATE(YEAR($H$3),MONTH($H$3),1),1)) -> 10850 | L16: =SUMIFS(Expenses!$E$4:$E$153,Expenses!$A$4:$A$153,">="&EDATE(DATE(YEAR($H$3),MONTH($H$3),1),0),Expenses!$A$4:$A$153,"<"&EDATE(DATE(YEAR($H$3),MONTH($H$3),1),1)) -> 2227.9 | M16: =K16-L16 -> 8622.1
J19: Category | K19: Amount
J20: Housing | K20: =SUMIFS(Expenses!$E$4:$E$153,Expenses!$C$4:$C$153,$J20,Expenses!$A$4:$A$153,">="&DATE(YEAR($H$3),MONTH($H$3),1),Expenses!$A$4:$A$153,"<"&EDATE(DATE(YEAR($H$3),MONTH($H$3),1),1)) -> 1800
J21: Food | K21: =SUMIFS(Expenses!$E$4:$E$153,Expenses!$C$4:$C$153,$J21,Expenses!$A$4:$A$153,">="&DATE(YEAR($H$3),MONTH($H$3),1),Expenses!$A$4:$A$153,"<"&EDATE(DATE(YEAR($H$3),MONTH($H$3),1),1)) -> 145.32
J22: Transport | K22: =SUMIFS(Expenses!$E$4:$E$153,Expenses!$C$4:$C$153,$J22,Expenses!$A$4:$A$153,">="&DATE(YEAR($H$3),MONTH($H$3),1),Expenses!$A$4:$A$153,"<"&EDATE(DATE(YEAR($H$3),MONTH($H$3),1),1)) -> 24.5
J23: Shopping | K23: =SUMIFS(Expenses!$E$4:$E$153,Expenses!$C$4:$C$153,$J23,Expenses!$A$4:$A$153,">="&DATE(YEAR($H$3),MONTH($H$3),1),Expenses!$A$4:$A$153,"<"&EDATE(DATE(YEAR($H$3),MONTH($H$3),1),1)) -> 89.99
J24: Health | K24: =SUMIFS(Expenses!$E$4:$E$153,Expenses!$C$4:$C$153,$J24,Expenses!$A$4:$A$153,">="&DATE(YEAR($H$3),MONTH($H$3),1),Expenses!$A$4:$A$153,"<"&EDATE(DATE(YEAR($H$3),MONTH($H$3),1),1)) -> 42.1
J25: Entertainment | K25: =SUMIFS(Expenses!$E$4:$E$153,Expenses!$C$4:$C$153,$J25,Expenses!$A$4:$A$153,">="&DATE(YEAR($H$3),MONTH($H$3),1),Expenses!$A$4:$A$153,"<"&EDATE(DATE(YEAR($H$3),MONTH($H$3),1),1)) -> 15.99
J26: Utilities | K26: =SUMIFS(Expenses!$E$4:$E$153,Expenses!$C$4:$C$153,$J26,Expenses!$A$4:$A$153,">="&DATE(YEAR($H$3),MONTH($H$3),1),Expenses!$A$4:$A$153,"<"&EDATE(DATE(YEAR($H$3),MONTH($H$3),1),1)) -> 110
J27: Other | K27: =SUMIFS(Expenses!$E$4:$E$153,Expenses!$C$4:$C$153,$J27,Expenses!$A$4:$A$153,">="&DATE(YEAR($H$3),MONTH($H$3),1),Expenses!$A$4:$A$153,"<"&EDATE(DATE(YEAR($H$3),MONTH($H$3),1),1)) -> 0

Sheet Income
A1: INCOME TRACKER
A2: Log every deposit — Dashboard updates automatically
A3: Date | B3: Source | C3: Category | D3: Amount | E3: Notes
A4: 46235 | B4: Acme Corp | C4: Salary | D4: 5200 | E4: Bi-weekly paycheck
A5: 46239 | B5: Freelance Client - Logo | C5: Freelance | D5: 450 | E5: Design project
A6: 46249 | B6: Acme Corp | C6: Salary | D6: 5200 | E6: Bi-weekly paycheck
C52: TOTAL | D52: =SUM(D4:D51) -> 10850

Sheet Expenses
A1: EXPENSE TRACKER
A2: Log every purchase — Dashboard updates automatically
A3: Date | B3: Merchant | C3: Category | D3: Payment Method | E3: Amount
A4: 46235 | B4: Landlord LLC | C4: Housing | D4: Bank Transfer | E4: 1800
A5: 46236 | B5: Whole Foods | C5: Food | D5: Credit Card | E5: 145.32
A6: 46237 | B6: Uber | C6: Transport | D6: Credit Card | E6: 24.5
A7: 46238 | B7: Amazon | C7: Shopping | D7: Credit Card | E7: 89.99
A8: 46240 | B8: City Electric | C8: Utilities | D8: Bank Transfer | E8: 110
A9: 46242 | B9: Netflix | C9: Entertainment | D9: Credit Card | E9: 15.99
A10: 46244 | B10: CVS Pharmacy | C10: Health | D10: Debit Card | E10: 42.1
D154: TOTAL | E154: =SUM(E4:E153) -> 2227.9

Sheet Bills
A1: BILLS TRACKER
A2: Overdue bills auto-highlight in red
A3: Bill Name | B3: Due Date | C3: Amount | D3: Status
A4: Rent | B4: 46235 | C4: 1800 | D4: Paid
A5: Electric Bill | B5: 46249 | C5: 110 | D5: Pending
A6: Internet | B6: 46244 | C6: 60 | D6: Paid
A7: Car Loan | B7: 46239 | C7: 320 | D7: Pending
A8: Phone Plan | B8: 46254 | C8: 55 | D8: Pending
A35: Legend:
A36: Red = Overdue & unpaid
A37: Green = Paid

Sheet Savings Goals
A1: SAVINGS GOALS
A2: Track progress toward every target
A3: Goal | B3: Target Amount | C3: Saved | D3: Remaining | E3: Progress %
A4: Emergency Fund | B4: 15000 | C4: 9000 | D4: =B4-C4 -> 6000 | E4: =IFERROR(C4/B4,0) -> 0.6
A5: Vacation - Japan | B5: 4000 | C5: 1200 | D5: =B5-C5 -> 2800 | E5: =IFERROR(C5/B5,0) -> 0.3
A6: New Laptop | B6: 2000 | C6: 2000 | D6: =B6-C6 -> 0 | E6: =IFERROR(C6/B6,0) -> 1
D7: =B7-C7 -> 0 | E7: =IFERROR(C7/B7,0) -> 0
D8: =B8-C8 -> 0 | E8: =IFERROR(C8/B8,0) -> 0
D9: =B9-C9 -> 0 | E9: =IFERROR(C9/B9,0) -> 0
D10: =B10-C10 -> 0 | E10: =IFERROR(C10/B10,0) -> 0
D11: =B11-C11 -> 0 | E11: =IFERROR(C11/B11,0) -> 0
D12: =B12-C12 -> 0 | E12: =IFERROR(C12/B12,0) -> 0
D13: =B13-C13 -> 0 | E13: =IFERROR(C13/B13,0) -> 0

Sheet Net Worth
A1: NET WORTH
A2: Assets vs Liabilities — updates automatically
A4: As Of Date | B4: =TODAY() -> 46253
A6: ASSETS | E6: LIABILITIES
A7: Type | B7: Description | C7: Value | E7: Type | F7: Description | G7: Value
A8: Cash & Bank | B8: Checking + Savings | C8: 12500 | E8: Credit Card | F8: Visa Balance | G8: 2200
A9: Investments | B9: Brokerage / Retirement | C9: 34000 | E9: Loan | F9: Car Loan Balance | G9: 8100
A10: Property | B10: Primary Residence | C10: 0 | E10: Mortgage | F10: Home Loan Balance | G10: 0
A11: Vehicle | B11: Car (est. resale) | C11: 9500
B18: TOTAL ASSETS | C18: =SUM(C8:C17) -> 56000 | F18: TOTAL LIABILITIES | G18: =SUM(G8:G17) -> 10300
A21: NET WORTH | E21: =C18-G18 -> 45700

Sheet Budget Planner
A1: BUDGET PLANNER
A2: Planned vs Actual spending by category (current report month)
A4: Report Month | B4: =Dashboard!$H$3 -> 46235
A6: Category | B6: Planned | C6: Actual | D6: Variance | E6: Variance %
A7: Housing | B7: 1800 | C7: =SUMIFS(Expenses!$E$4:$E$153,Expenses!$C$4:$C$153,$A7,Expenses!$A$4:$A$153,">="&DATE(YEAR($B$4),MONTH($B$4),1),Expenses!$A$4:$A$153,"<"&EDATE(DATE(YEAR($B$4),MONTH($B$4),1),1)) -> 1800 | D7: =B7-C7 -> 0 | E7: =IFERROR(D7/B7,0) -> 0
A8: Food | B8: 600 | C8: =SUMIFS(Expenses!$E$4:$E$153,Expenses!$C$4:$C$153,$A8,Expenses!$A$4:$A$153,">="&DATE(YEAR($B$4),MONTH($B$4),1),Expenses!$A$4:$A$153,"<"&EDATE(DATE(YEAR($B$4),MONTH($B$4),1),1)) -> 145.32 | D8: =B8-C8 -> 454.68 | E8: =IFERROR(D8/B8,0) -> 0.7578
A9: Transport | B9: 200 | C9: =SUMIFS(Expenses!$E$4:$E$153,Expenses!$C$4:$C$153,$A9,Expenses!$A$4:$A$153,">="&DATE(YEAR($B$4),MONTH($B$4),1),Expenses!$A$4:$A$153,"<"&EDATE(DATE(YEAR($B$4),MONTH($B$4),1),1)) -> 24.5 | D9: =B9-C9 -> 175.5 | E9: =IFERROR(D9/B9,0) -> 0.8775
A10: Shopping | B10: 250 | C10: =SUMIFS(Expenses!$E$4:$E$153,Expenses!$C$4:$C$153,$A10,Expenses!$A$4:$A$153,">="&DATE(YEAR($B$4),MONTH($B$4),1),Expenses!$A$4:$A$153,"<"&EDATE(DATE(YEAR($B$4),MONTH($B$4),1),1)) -> 89.99 | D10: =B10-C10 -> 160.01 | E10: =IFERROR(D10/B10,0) -> 0.64004
A11: Health | B11: 150 | C11: =SUMIFS(Expenses!$E$4:$E$153,Expenses!$C$4:$C$153,$A11,Expenses!$A$4:$A$153,">="&DATE(YEAR($B$4),MONTH($B$4),1),Expenses!$A$4:$A$153,"<"&EDATE(DATE(YEAR($B$4),MONTH($B$4),1),1)) -> 42.1 | D11: =B11-C11 -> 107.9 | E11: =IFERROR(D11/B11,0) -> 0.71933333
A12: Entertainment | B12: 100 | C12: =SUMIFS(Expenses!$E$4:$E$153,Expenses!$C$4:$C$153,$A12,Expenses!$A$4:$A$153,">="&DATE(YEAR($B$4),MONTH($B$4),1),Expenses!$A$4:$A$153,"<"&EDATE(DATE(YEAR($B$4),MONTH($B$4),1),1)) -> 15.99 | D12: =B12-C12 -> 84.01 | E12: =IFERROR(D12/B12,0) -> 0.8401
A13: Utilities | B13: 180 | C13: =SUMIFS(Expenses!$E$4:$E$153,Expenses!$C$4:$C$153,$A13,Expenses!$A$4:$A$153,">="&DATE(YEAR($B$4),MONTH($B$4),1),Expenses!$A$4:$A$153,"<"&EDATE(DATE(YEAR($B$4),MONTH($B$4),1),1)) -> 110 | D13: =B13-C13 -> 70 | E13: =IFERROR(D13/B13,0) -> 0.38888889
A14: Other | B14: 100 | C14: =SUMIFS(Expenses!$E$4:$E$153,Expenses!$C$4:$C$153,$A14,Expenses!$A$4:$A$153,">="&DATE(YEAR($B$4),MONTH($B$4),1),Expenses!$A$4:$A$153,"<"&EDATE(DATE(YEAR($B$4),MONTH($B$4),1),1)) -> 0 | D14: =B14-C14 -> 100 | E14: =IFERROR(D14/B14,0) -> 1
A15: TOTAL | B15: =SUM(B7:B14) -> 3380 | C15: =SUM(C7:C14) -> 2227.9 | D15: =SUM(D7:D14) -> 1152.1 | E15: =IFERROR(D15/B15,0) -> 0.34085799

Sheet Settings
A1: SETTINGS | H1: Expense Categories | I1: Income Categories | J1: Payment Methods | K1: Bill Status | L1: Asset Types | M1: Liability Types
A2: Ultimate Finance OS — Configuration | H2: Housing | I2: Salary | J2: Cash | K2: Paid | L2: Cash & Bank | M2: Credit Card
H3: Food | I3: Freelance | J3: Credit Card | K3: Pending | L3: Investments | M3: Loan
A4: GENERAL | H4: Transport | I4: Business | J4: Debit Card | L4: Property | M4: Mortgage
A5: User Name | B5: Your Name | H5: Shopping | I5: Investment | J5: Bank Transfer | L5: Vehicle | M5: Other
A6: Currency | B6: USD | H6: Health | I6: Gift | J6: Other | L6: Other
A7: Start Month | B7: =DATE(YEAR(TODAY()),MONTH(TODAY()),1) -> 46235 | H7: Entertainment | I7: Other
A8: Theme | B8: Premium Dark | H8: Utilities
A9: Version | B9: 1.0 | H9: Other
A10: SKU | B10: DPS-XLS-001
A12: Blue text on light-yellow = editable input cell. Update these values to personalize your workbook.
